deephaven_plugin_notebook/__init__.py
deephaven_plugin_notebook/deephaven_plugin_notebook_object.py
deephaven_plugin_notebook/deephaven_plugin_notebook_type.py
deephaven_plugin_notebook/js_plugin.py
deephaven_plugin_notebook/register.py
deephaven_plugin_notebook/_js/package.json
deephaven_plugin_notebook/_js/dist/index.js
deephaven_plugin_notebook-0.0.1.dist-info/LICENSE
deephaven_plugin_notebook-0.0.1.dist-info/METADATA
deephaven_plugin_notebook-0.0.1.dist-info/WHEEL
deephaven_plugin_notebook-0.0.1.dist-info/entry_points.txt
deephaven_plugin_notebook-0.0.1.dist-info/top_level.txt
deephaven_plugin_notebook-0.0.1.dist-info/RECORD
